passwork/__init__.py
passwork/main.py
passwork/passwork_api.py
passwork/session_options.py
passwork/password_crud/__init__.py
passwork/password_crud/add_password.py
passwork/password_crud/delete_password.py
passwork/password_crud/get_inbox_password.py
passwork/password_crud/get_password.py
passwork/password_crud/search_password.py
passwork/rest_modules/__init__.py
passwork/rest_modules/passwords.py
passwork/rest_modules/users.py
passwork/rest_modules/vaults.py
passwork/utils/__init__.py
passwork/utils/base32.py
passwork/utils/crypto_file.py
passwork/utils/crypto_interface.py
passwork/utils/passwork_utils.py
passworkconnectortest-0.1.6.dist-info/LICENSE
passworkconnectortest-0.1.6.dist-info/METADATA
passworkconnectortest-0.1.6.dist-info/WHEEL
passworkconnectortest-0.1.6.dist-info/top_level.txt
passworkconnectortest-0.1.6.dist-info/RECORD
