Metadata-Version: 2.1
Name: passworkconnectortest
Version: 0.1.6
Summary: Passwork API connector
Requires-Python: >=3.10
License-File: LICENSE
Requires-Dist: requests >=2.31.0
Requires-Dist: cryptography >=42.0.5
Requires-Dist: loguru >=0.7.2
